[
  {
    "order_id": "d34433cef5e24007",
    "tradingsymbol": "NIFTY25092525000CE",
    "transaction_type": "BUY",
    "quantity": 50,
    "order_type": "MARKET",
    "price": 0.0,
    "product": "NRML",
    "status": "COMPLETE",
    "status_message": "Order completed successfully",
    "order_timestamp": "2025-08-03T22:39:20.196979",
    "exchange_timestamp": "2025-08-03T22:39:20.196988",
    "filled_quantity": 50,
    "pending_quantity": 0,
    "cancelled_quantity": 0,
    "average_price": 100.0,
    "exchange": "NFO",
    "validity": "DAY",
    "variety": "regular",
    "tag": null
  },
  {
    "order_id": "560c2ab3c732452c",
    "tradingsymbol": "NIFTY25092525100PE",
    "transaction_type": "SELL",
    "quantity": 25,
    "order_type": "MARKET",
    "price": 0.0,
    "product": "NRML",
    "status": "COMPLETE",
    "status_message": "Order completed successfully",
    "order_timestamp": "2025-08-03T22:41:58.667212",
    "exchange_timestamp": "2025-08-03T22:41:58.667218",
    "filled_quantity": 25,
    "pending_quantity": 0,
    "cancelled_quantity": 0,
    "average_price": 100.0,
    "exchange": "NFO",
    "validity": "DAY",
    "variety": "regular",
    "tag": null
  },
  {
    "order_id": "be8d35e1a11f4ce1",
    "tradingsymbol": "TEST456PE",
    "transaction_type": "SELL",
    "quantity": 25,
    "order_type": "MARKET",
    "price": 0.0,
    "product": "NRML",
    "status": "COMPLETE",
    "status_message": "Order completed successfully",
    "order_timestamp": "2025-08-03T22:42:12.453897",
    "exchange_timestamp": "2025-08-03T22:42:12.453904",
    "filled_quantity": 25,
    "pending_quantity": 0,
    "cancelled_quantity": 0,
    "average_price": 100.0,
    "exchange": "NFO",
    "validity": "DAY",
    "variety": "regular",
    "tag": null
  },
  {
    "order_id": "a3a07f90d6714a80",
    "tradingsymbol": "TESTORDER123CE",
    "transaction_type": "BUY",
    "quantity": 25,
    "order_type": "MARKET",
    "price": 0.0,
    "product": "NRML",
    "status": "COMPLETE",
    "status_message": "Order completed successfully",
    "order_timestamp": "2025-08-03T22:44:14.202972",
    "exchange_timestamp": "2025-08-03T22:44:14.202978",
    "filled_quantity": 25,
    "pending_quantity": 0,
    "cancelled_quantity": 0,
    "average_price": 100.0,
    "exchange": "NFO",
    "validity": "DAY",
    "variety": "regular",
    "tag": null
  },
  {
    "order_id": "2d9ceb1df55c4b2f",
    "tradingsymbol": "NIFTY25092525000CE",
    "transaction_type": "SELL",
    "quantity": 50,
    "order_type": "MARKET",
    "price": 0.0,
    "product": "NRML",
    "status": "COMPLETE",
    "status_message": "Order completed successfully",
    "order_timestamp": "2025-08-03T23:22:47.552130",
    "exchange_timestamp": "2025-08-03T23:22:47.552133",
    "filled_quantity": 50,
    "pending_quantity": 0,
    "cancelled_quantity": 0,
    "average_price": 100.0,
    "exchange": "NFO",
    "validity": "DAY",
    "variety": "regular",
    "tag": null
  },
  {
    "order_id": "933d57c7a8524a3c",
    "tradingsymbol": "NIFTY25092524550CE",
    "transaction_type": "BUY",
    "quantity": 50,
    "order_type": "MARKET",
    "price": 0.0,
    "product": "NRML",
    "status": "COMPLETE",
    "status_message": "Order completed successfully",
    "order_timestamp": "2025-08-03T23:22:47.552492",
    "exchange_timestamp": "2025-08-03T23:22:47.552493",
    "filled_quantity": 50,
    "pending_quantity": 0,
    "cancelled_quantity": 0,
    "average_price": 100.0,
    "exchange": "NFO",
    "validity": "DAY",
    "variety": "regular",
    "tag": null
  },
  {
    "order_id": "96a45dc6f00748b2",
    "tradingsymbol": "NIFTY25092525100PE",
    "transaction_type": "BUY",
    "quantity": 25,
    "order_type": "MARKET",
    "price": 0.0,
    "product": "NRML",
    "status": "COMPLETE",
    "status_message": "Order completed successfully",
    "order_timestamp": "2025-08-03T23:22:47.552728",
    "exchange_timestamp": "2025-08-03T23:22:47.552729",
    "filled_quantity": 25,
    "pending_quantity": 0,
    "cancelled_quantity": 0,
    "average_price": 100.0,
    "exchange": "NFO",
    "validity": "DAY",
    "variety": "regular",
    "tag": null
  },
  {
    "order_id": "12a162ed3ed8466f",
    "tradingsymbol": "NIFTY25080724350PE",
    "transaction_type": "SELL",
    "quantity": 50,
    "order_type": "MARKET",
    "price": 0.0,
    "product": "NRML",
    "status": "COMPLETE",
    "status_message": "Order completed successfully",
    "order_timestamp": "2025-08-03T23:47:25.502974",
    "exchange_timestamp": "2025-08-03T23:47:25.502976",
    "filled_quantity": 50,
    "pending_quantity": 0,
    "cancelled_quantity": 0,
    "average_price": 100.0,
    "exchange": "NFO",
    "validity": "DAY",
    "variety": "regular",
    "tag": null
  },
  {
    "order_id": "b8847de7973f4065",
    "tradingsymbol": "NIFTY25080724350CE",
    "transaction_type": "SELL",
    "quantity": 50,
    "order_type": "MARKET",
    "price": 0.0,
    "product": "NRML",
    "status": "COMPLETE",
    "status_message": "Order completed successfully",
    "order_timestamp": "2025-08-03T23:47:25.503671",
    "exchange_timestamp": "2025-08-03T23:47:25.503674",
    "filled_quantity": 50,
    "pending_quantity": 0,
    "cancelled_quantity": 0,
    "average_price": 100.0,
    "exchange": "NFO",
    "validity": "DAY",
    "variety": "regular",
    "tag": null
  },
  {
    "order_id": "8e1cffb179bd4842",
    "tradingsymbol": "NIFTY25092524350PE",
    "transaction_type": "BUY",
    "quantity": 50,
    "order_type": "MARKET",
    "price": 0.0,
    "product": "NRML",
    "status": "COMPLETE",
    "status_message": "Order completed successfully",
    "order_timestamp": "2025-08-03T23:47:25.504090",
    "exchange_timestamp": "2025-08-03T23:47:25.504095",
    "filled_quantity": 50,
    "pending_quantity": 0,
    "cancelled_quantity": 0,
    "average_price": 100.0,
    "exchange": "NFO",
    "validity": "DAY",
    "variety": "regular",
    "tag": null
  },
  {
    "order_id": "7c9db7b11b0b4e47",
    "tradingsymbol": "NIFTY25092525650CE",
    "transaction_type": "BUY",
    "quantity": 50,
    "order_type": "MARKET",
    "price": 0.0,
    "product": "NRML",
    "status": "COMPLETE",
    "status_message": "Order completed successfully",
    "order_timestamp": "2025-08-03T23:47:25.504366",
    "exchange_timestamp": "2025-08-03T23:47:25.504368",
    "filled_quantity": 50,
    "pending_quantity": 0,
    "cancelled_quantity": 0,
    "average_price": 100.0,
    "exchange": "NFO",
    "validity": "DAY",
    "variety": "regular",
    "tag": null
  },
  {
    "order_id": "41e3bd7783a44072",
    "tradingsymbol": "NIFTY25080725550PE",
    "transaction_type": "SELL",
    "quantity": 50,
    "order_type": "MARKET",
    "price": 0.0,
    "product": "NRML",
    "status": "COMPLETE",
    "status_message": "Order completed successfully",
    "order_timestamp": "2025-08-03T23:47:38.891755",
    "exchange_timestamp": "2025-08-03T23:47:38.891758",
    "filled_quantity": 50,
    "pending_quantity": 0,
    "cancelled_quantity": 0,
    "average_price": 100.0,
    "exchange": "NFO",
    "validity": "DAY",
    "variety": "regular",
    "tag": null
  },
  {
    "order_id": "68b711a399b04068",
    "tradingsymbol": "NIFTY25080725550CE",
    "transaction_type": "SELL",
    "quantity": 50,
    "order_type": "MARKET",
    "price": 0.0,
    "product": "NRML",
    "status": "COMPLETE",
    "status_message": "Order completed successfully",
    "order_timestamp": "2025-08-03T23:47:38.892275",
    "exchange_timestamp": "2025-08-03T23:47:38.892277",
    "filled_quantity": 50,
    "pending_quantity": 0,
    "cancelled_quantity": 0,
    "average_price": 100.0,
    "exchange": "NFO",
    "validity": "DAY",
    "variety": "regular",
    "tag": null
  },
  {
    "order_id": "f12b9bb88e8c4f49",
    "tradingsymbol": "NIFTY25092525600CE",
    "transaction_type": "BUY",
    "quantity": 50,
    "order_type": "MARKET",
    "price": 0.0,
    "product": "NRML",
    "status": "COMPLETE",
    "status_message": "Order completed successfully",
    "order_timestamp": "2025-08-03T23:47:38.892820",
    "exchange_timestamp": "2025-08-03T23:47:38.892824",
    "filled_quantity": 50,
    "pending_quantity": 0,
    "cancelled_quantity": 0,
    "average_price": 100.0,
    "exchange": "NFO",
    "validity": "DAY",
    "variety": "regular",
    "tag": null
  },
  {
    "order_id": "e56a1be8df8c431f",
    "tradingsymbol": "NIFTY25080724450PE",
    "transaction_type": "SELL",
    "quantity": 50,
    "order_type": "MARKET",
    "price": 0.0,
    "product": "NRML",
    "status": "COMPLETE",
    "status_message": "Order completed successfully",
    "order_timestamp": "2025-08-03T23:47:41.958018",
    "exchange_timestamp": "2025-08-03T23:47:41.958033",
    "filled_quantity": 50,
    "pending_quantity": 0,
    "cancelled_quantity": 0,
    "average_price": 100.0,
    "exchange": "NFO",
    "validity": "DAY",
    "variety": "regular",
    "tag": null
  },
  {
    "order_id": "67803bb357e743f9",
    "tradingsymbol": "NIFTY25080724450CE",
    "transaction_type": "SELL",
    "quantity": 50,
    "order_type": "MARKET",
    "price": 0.0,
    "product": "NRML",
    "status": "COMPLETE",
    "status_message": "Order completed successfully",
    "order_timestamp": "2025-08-03T23:47:41.959450",
    "exchange_timestamp": "2025-08-03T23:47:41.959456",
    "filled_quantity": 50,
    "pending_quantity": 0,
    "cancelled_quantity": 0,
    "average_price": 100.0,
    "exchange": "NFO",
    "validity": "DAY",
    "variety": "regular",
    "tag": null
  },
  {
    "order_id": "d3c722c3ca544821",
    "tradingsymbol": "NIFTY25092524050PE",
    "transaction_type": "BUY",
    "quantity": 50,
    "order_type": "MARKET",
    "price": 0.0,
    "product": "NRML",
    "status": "COMPLETE",
    "status_message": "Order completed successfully",
    "order_timestamp": "2025-08-03T23:47:41.960715",
    "exchange_timestamp": "2025-08-03T23:47:41.960733",
    "filled_quantity": 50,
    "pending_quantity": 0,
    "cancelled_quantity": 0,
    "average_price": 100.0,
    "exchange": "NFO",
    "validity": "DAY",
    "variety": "regular",
    "tag": null
  },
  {
    "order_id": "b5967068962d43e1",
    "tradingsymbol": "NIFTY25092525850CE",
    "transaction_type": "BUY",
    "quantity": 50,
    "order_type": "MARKET",
    "price": 0.0,
    "product": "NRML",
    "status": "COMPLETE",
    "status_message": "Order completed successfully",
    "order_timestamp": "2025-08-03T23:47:41.961544",
    "exchange_timestamp": "2025-08-03T23:47:41.961548",
    "filled_quantity": 50,
    "pending_quantity": 0,
    "cancelled_quantity": 0,
    "average_price": 100.0,
    "exchange": "NFO",
    "validity": "DAY",
    "variety": "regular",
    "tag": null
  },
  {
    "order_id": "ddf8eb7c0ed943f6",
    "tradingsymbol": "NIFTY25080723900PE",
    "transaction_type": "SELL",
    "quantity": 50,
    "order_type": "MARKET",
    "price": 0.0,
    "product": "NRML",
    "status": "COMPLETE",
    "status_message": "Order completed successfully",
    "order_timestamp": "2025-08-03T23:47:45.024733",
    "exchange_timestamp": "2025-08-03T23:47:45.024741",
    "filled_quantity": 50,
    "pending_quantity": 0,
    "cancelled_quantity": 0,
    "average_price": 100.0,
    "exchange": "NFO",
    "validity": "DAY",
    "variety": "regular",
    "tag": null
  },
  {
    "order_id": "65a987525a6a4706",
    "tradingsymbol": "NIFTY25080723900CE",
    "transaction_type": "SELL",
    "quantity": 50,
    "order_type": "MARKET",
    "price": 0.0,
    "product": "NRML",
    "status": "COMPLETE",
    "status_message": "Order completed successfully",
    "order_timestamp": "2025-08-03T23:47:45.025253",
    "exchange_timestamp": "2025-08-03T23:47:45.025255",
    "filled_quantity": 50,
    "pending_quantity": 0,
    "cancelled_quantity": 0,
    "average_price": 100.0,
    "exchange": "NFO",
    "validity": "DAY",
    "variety": "regular",
    "tag": null
  },
  {
    "order_id": "b37ba89a4dff4b9f",
    "tradingsymbol": "NIFTY25092525450CE",
    "transaction_type": "BUY",
    "quantity": 50,
    "order_type": "MARKET",
    "price": 0.0,
    "product": "NRML",
    "status": "COMPLETE",
    "status_message": "Order completed successfully",
    "order_timestamp": "2025-08-03T23:47:45.026132",
    "exchange_timestamp": "2025-08-03T23:47:45.026151",
    "filled_quantity": 50,
    "pending_quantity": 0,
    "cancelled_quantity": 0,
    "average_price": 100.0,
    "exchange": "NFO",
    "validity": "DAY",
    "variety": "regular",
    "tag": null
  },
  {
    "order_id": "08656bfac0bc4a61",
    "tradingsymbol": "NIFTY25080725350PE",
    "transaction_type": "SELL",
    "quantity": 50,
    "order_type": "MARKET",
    "price": 0.0,
    "product": "NRML",
    "status": "COMPLETE",
    "status_message": "Order completed successfully",
    "order_timestamp": "2025-08-03T23:48:59.388615",
    "exchange_timestamp": "2025-08-03T23:48:59.388617",
    "filled_quantity": 50,
    "pending_quantity": 0,
    "cancelled_quantity": 0,
    "average_price": 100.0,
    "exchange": "NFO",
    "validity": "DAY",
    "variety": "regular",
    "tag": null
  },
  {
    "order_id": "a81fbb699dd54990",
    "tradingsymbol": "NIFTY25080725350CE",
    "transaction_type": "SELL",
    "quantity": 50,
    "order_type": "MARKET",
    "price": 0.0,
    "product": "NRML",
    "status": "COMPLETE",
    "status_message": "Order completed successfully",
    "order_timestamp": "2025-08-03T23:48:59.389292",
    "exchange_timestamp": "2025-08-03T23:48:59.389295",
    "filled_quantity": 50,
    "pending_quantity": 0,
    "cancelled_quantity": 0,
    "average_price": 100.0,
    "exchange": "NFO",
    "validity": "DAY",
    "variety": "regular",
    "tag": null
  },
  {
    "order_id": "f14ed4c4172546bd",
    "tradingsymbol": "NIFTY25092524150PE",
    "transaction_type": "BUY",
    "quantity": 50,
    "order_type": "MARKET",
    "price": 0.0,
    "product": "NRML",
    "status": "COMPLETE",
    "status_message": "Order completed successfully",
    "order_timestamp": "2025-08-03T23:48:59.390308",
    "exchange_timestamp": "2025-08-03T23:48:59.390310",
    "filled_quantity": 50,
    "pending_quantity": 0,
    "cancelled_quantity": 0,
    "average_price": 100.0,
    "exchange": "NFO",
    "validity": "DAY",
    "variety": "regular",
    "tag": null
  },
  {
    "order_id": "a3d26da36ee44dcd",
    "tradingsymbol": "NIFTY25092524400PE",
    "transaction_type": "BUY",
    "quantity": 50,
    "order_type": "MARKET",
    "price": 0.0,
    "product": "NRML",
    "status": "COMPLETE",
    "status_message": "Order completed successfully",
    "order_timestamp": "2025-08-03T23:49:02.450710",
    "exchange_timestamp": "2025-08-03T23:49:02.450717",
    "filled_quantity": 50,
    "pending_quantity": 0,
    "cancelled_quantity": 0,
    "average_price": 100.0,
    "exchange": "NFO",
    "validity": "DAY",
    "variety": "regular",
    "tag": null
  },
  {
    "order_id": "04f638af06874a36",
    "tradingsymbol": "NIFTY25092525800CE",
    "transaction_type": "BUY",
    "quantity": 50,
    "order_type": "MARKET",
    "price": 0.0,
    "product": "NRML",
    "status": "COMPLETE",
    "status_message": "Order completed successfully",
    "order_timestamp": "2025-08-03T23:49:02.451395",
    "exchange_timestamp": "2025-08-03T23:49:02.451397",
    "filled_quantity": 50,
    "pending_quantity": 0,
    "cancelled_quantity": 0,
    "average_price": 100.0,
    "exchange": "NFO",
    "validity": "DAY",
    "variety": "regular",
    "tag": null
  },
  {
    "order_id": "380b319d88de4390",
    "tradingsymbol": "NIFTY25080725400PE",
    "transaction_type": "SELL",
    "quantity": 50,
    "order_type": "MARKET",
    "price": 0.0,
    "product": "NRML",
    "status": "COMPLETE",
    "status_message": "Order completed successfully",
    "order_timestamp": "2025-08-03T23:49:05.987498",
    "exchange_timestamp": "2025-08-03T23:49:05.987500",
    "filled_quantity": 50,
    "pending_quantity": 0,
    "cancelled_quantity": 0,
    "average_price": 100.0,
    "exchange": "NFO",
    "validity": "DAY",
    "variety": "regular",
    "tag": null
  },
  {
    "order_id": "14b0603a38ea4799",
    "tradingsymbol": "NIFTY25080725400CE",
    "transaction_type": "SELL",
    "quantity": 50,
    "order_type": "MARKET",
    "price": 0.0,
    "product": "NRML",
    "status": "COMPLETE",
    "status_message": "Order completed successfully",
    "order_timestamp": "2025-08-03T23:49:05.988212",
    "exchange_timestamp": "2025-08-03T23:49:05.988215",
    "filled_quantity": 50,
    "pending_quantity": 0,
    "cancelled_quantity": 0,
    "average_price": 100.0,
    "exchange": "NFO",
    "validity": "DAY",
    "variety": "regular",
    "tag": null
  },
  {
    "order_id": "844bb12211054278",
    "tradingsymbol": "NIFTY25092524450PE",
    "transaction_type": "BUY",
    "quantity": 50,
    "order_type": "MARKET",
    "price": 0.0,
    "product": "NRML",
    "status": "COMPLETE",
    "status_message": "Order completed successfully",
    "order_timestamp": "2025-08-03T23:49:05.989272",
    "exchange_timestamp": "2025-08-03T23:49:05.989274",
    "filled_quantity": 50,
    "pending_quantity": 0,
    "cancelled_quantity": 0,
    "average_price": 100.0,
    "exchange": "NFO",
    "validity": "DAY",
    "variety": "regular",
    "tag": null
  },
  {
    "order_id": "c637904820d74b67",
    "tradingsymbol": "NIFTY25080725200PE",
    "transaction_type": "SELL",
    "quantity": 50,
    "order_type": "MARKET",
    "price": 0.0,
    "product": "NRML",
    "status": "COMPLETE",
    "status_message": "Order completed successfully",
    "order_timestamp": "2025-08-03T23:49:09.049573",
    "exchange_timestamp": "2025-08-03T23:49:09.049586",
    "filled_quantity": 50,
    "pending_quantity": 0,
    "cancelled_quantity": 0,
    "average_price": 100.0,
    "exchange": "NFO",
    "validity": "DAY",
    "variety": "regular",
    "tag": null
  },
  {
    "order_id": "d38158718fc442d8",
    "tradingsymbol": "NIFTY25080725200CE",
    "transaction_type": "SELL",
    "quantity": 50,
    "order_type": "MARKET",
    "price": 0.0,
    "product": "NRML",
    "status": "COMPLETE",
    "status_message": "Order completed successfully",
    "order_timestamp": "2025-08-03T23:49:09.051189",
    "exchange_timestamp": "2025-08-03T23:49:09.051195",
    "filled_quantity": 50,
    "pending_quantity": 0,
    "cancelled_quantity": 0,
    "average_price": 100.0,
    "exchange": "NFO",
    "validity": "DAY",
    "variety": "regular",
    "tag": null
  },
  {
    "order_id": "c2d9612c14404941",
    "tradingsymbol": "NIFTY25092524000PE",
    "transaction_type": "BUY",
    "quantity": 50,
    "order_type": "MARKET",
    "price": 0.0,
    "product": "NRML",
    "status": "COMPLETE",
    "status_message": "Order completed successfully",
    "order_timestamp": "2025-08-03T23:49:09.052354",
    "exchange_timestamp": "2025-08-03T23:49:09.052358",
    "filled_quantity": 50,
    "pending_quantity": 0,
    "cancelled_quantity": 0,
    "average_price": 100.0,
    "exchange": "NFO",
    "validity": "DAY",
    "variety": "regular",
    "tag": null
  },
  {
    "order_id": "faf15eb02e4a4fe7",
    "tradingsymbol": "NIFTY25092525700CE",
    "transaction_type": "BUY",
    "quantity": 50,
    "order_type": "MARKET",
    "price": 0.0,
    "product": "NRML",
    "status": "COMPLETE",
    "status_message": "Order completed successfully",
    "order_timestamp": "2025-08-03T23:49:09.053449",
    "exchange_timestamp": "2025-08-03T23:49:09.053452",
    "filled_quantity": 50,
    "pending_quantity": 0,
    "cancelled_quantity": 0,
    "average_price": 100.0,
    "exchange": "NFO",
    "validity": "DAY",
    "variety": "regular",
    "tag": null
  },
  {
    "order_id": "64dd6f9abd744239",
    "tradingsymbol": "NIFTY25080725850PE",
    "transaction_type": "SELL",
    "quantity": 50,
    "order_type": "MARKET",
    "price": 0.0,
    "product": "NRML",
    "status": "COMPLETE",
    "status_message": "Order completed successfully",
    "order_timestamp": "2025-08-03T23:49:12.116547",
    "exchange_timestamp": "2025-08-03T23:49:12.116556",
    "filled_quantity": 50,
    "pending_quantity": 0,
    "cancelled_quantity": 0,
    "average_price": 100.0,
    "exchange": "NFO",
    "validity": "DAY",
    "variety": "regular",
    "tag": null
  },
  {
    "order_id": "60f513c61ac54c8f",
    "tradingsymbol": "NIFTY25080725850CE",
    "transaction_type": "SELL",
    "quantity": 50,
    "order_type": "MARKET",
    "price": 0.0,
    "product": "NRML",
    "status": "COMPLETE",
    "status_message": "Order completed successfully",
    "order_timestamp": "2025-08-03T23:49:12.117583",
    "exchange_timestamp": "2025-08-03T23:49:12.117588",
    "filled_quantity": 50,
    "pending_quantity": 0,
    "cancelled_quantity": 0,
    "average_price": 100.0,
    "exchange": "NFO",
    "validity": "DAY",
    "variety": "regular",
    "tag": null
  },
  {
    "order_id": "1650f1210673438e",
    "tradingsymbol": "NIFTY25092526050CE",
    "transaction_type": "BUY",
    "quantity": 50,
    "order_type": "MARKET",
    "price": 0.0,
    "product": "NRML",
    "status": "COMPLETE",
    "status_message": "Order completed successfully",
    "order_timestamp": "2025-08-03T23:49:12.118334",
    "exchange_timestamp": "2025-08-03T23:49:12.118336",
    "filled_quantity": 50,
    "pending_quantity": 0,
    "cancelled_quantity": 0,
    "average_price": 100.0,
    "exchange": "NFO",
    "validity": "DAY",
    "variety": "regular",
    "tag": null
  },
  {
    "order_id": "8b4bc77aab5640f7",
    "tradingsymbol": "NIFTY25080725150PE",
    "transaction_type": "SELL",
    "quantity": 50,
    "order_type": "MARKET",
    "price": 0.0,
    "product": "NRML",
    "status": "COMPLETE",
    "status_message": "Order completed successfully",
    "order_timestamp": "2025-08-03T23:49:15.180664",
    "exchange_timestamp": "2025-08-03T23:49:15.180671",
    "filled_quantity": 50,
    "pending_quantity": 0,
    "cancelled_quantity": 0,
    "average_price": 100.0,
    "exchange": "NFO",
    "validity": "DAY",
    "variety": "regular",
    "tag": null
  },
  {
    "order_id": "318b2de398884df1",
    "tradingsymbol": "NIFTY25080725150CE",
    "transaction_type": "SELL",
    "quantity": 50,
    "order_type": "MARKET",
    "price": 0.0,
    "product": "NRML",
    "status": "COMPLETE",
    "status_message": "Order completed successfully",
    "order_timestamp": "2025-08-03T23:49:15.181567",
    "exchange_timestamp": "2025-08-03T23:49:15.181572",
    "filled_quantity": 50,
    "pending_quantity": 0,
    "cancelled_quantity": 0,
    "average_price": 100.0,
    "exchange": "NFO",
    "validity": "DAY",
    "variety": "regular",
    "tag": null
  },
  {
    "order_id": "a2c58f8608394545",
    "tradingsymbol": "NIFTY25092524600PE",
    "transaction_type": "BUY",
    "quantity": 50,
    "order_type": "MARKET",
    "price": 0.0,
    "product": "NRML",
    "status": "COMPLETE",
    "status_message": "Order completed successfully",
    "order_timestamp": "2025-08-03T23:49:15.182146",
    "exchange_timestamp": "2025-08-03T23:49:15.182148",
    "filled_quantity": 50,
    "pending_quantity": 0,
    "cancelled_quantity": 0,
    "average_price": 100.0,
    "exchange": "NFO",
    "validity": "DAY",
    "variety": "regular",
    "tag": null
  }
]